Workbook

Sheet Sheet1(after xlookup)
A1: Title | B1: Lead Actor | C1: Director Name | D1: Lead Actor FB Likes | E1: Cast FB Likes | F1: Director FB Likes | G1: Movie FB Likes | H1: IMDb Score (1-10) | I1: Total Reviews | J1: Duration (min) | K1: Gross Revenue | L1: Budget | M1: {=_xlfn.XLOOKUP(A1,Sheet2!$A$1:$A$3726,Sheet2!$B$1:$G$3726)} -> Release Date | N1: Color/B&W | O1: Genre | P1: Language | Q1: Country | R1: Rating | S1: is_english | T1: Profit | U1: %Profit | V1: duration_class
A2: [Rec] 2 | B2: Jonathan D. Mellor | C2: Jaume BalaguerÃ³ | D2: 37 | E2: 73 | F2: 57 | G2: 4000 | H2: 6.6 | I2: 222 | J2: 85 | K2: 27024 | L2: 5600000 | M2: {=_xlfn.XLOOKUP(A2,Sheet2!$A$1:$A$3726,Sheet2!$B$1:$G$3726)} -> 39921 | N2: Color | O2: Horror | P2: Spanish | Q2: Spain | R2: R
A3: 10 Days in a Madhouse | B3: Christopher Lambert | C3: Timothy Hines | D3: 1000 | E3: 2059 | F3: 0 | G3: 26000 | H3: 7.5 | I3: 1 | J3: 111 | K3: 14616 | L3: 12000000 | M3: {=_xlfn.XLOOKUP(A3,Sheet2!$A$1:$A$3726,Sheet2!$B$1:$G$3726)} -> 42130 | N3: Color | O3: Drama | P3: English | Q3: USA | R3: R
A4: 10 Things I Hate About You | B4: Joseph Gordon-Levitt | C4: Gil Junger | D4: 23000 | E4: 37907 | F4: 19 | G4: 10000 | H4: 7.2 | I4: 133 | J4: 97 | K4: 38176108 | L4: 16000000 | M4: {=_xlfn.XLOOKUP(A4,Sheet2!$A$1:$A$3726,Sheet2!$B$1:$G$3726)} -> 36245 | N4: Color | O4: Comedy | P4: English | Q4: USA | R4: PG-13
A5: 102 Dalmatians | B5: Ioan Gruffudd | C5: Kevin Lima | D5: 2000 | E5: 4182 | F5: 36 | G5: 372 | H5: 4.8 | I5: 84 | J5: 100 | K5: 66941559 | L5: 85000000 | M5: {=_xlfn.XLOOKUP(A5,Sheet2!$A$1:$A$3726,Sheet2!$B$1:$G$3726)} -> 36715 | N5: Color | O5: Adventure | P5: English | Q5: USA | R5: G
A6: 10th & Wolf | B6: Brian Dennehy | C6: Robert Moresco | D6: 954 | E6: 2512 | F6: 53 | G6: 294 | H6: 6.4 | I6: 26 | J6: 107 | K6: 53481 | L6: 8000000 | M6: {=_xlfn.XLOOKUP(A6,Sheet2!$A$1:$A$3726,Sheet2!$B$1:$G$3726)} -> 38850 | N6: Color | O6: Crime | P6: English | Q6: USA | R6: R
A7: 12 Rounds | B7: Taylor Cole | C7: Renny Harlin | D7: 969 | E7: 2799 | F7: 212 | G7: 0 | H7: 5.6 | I7: 113 | J7: 108 | K7: 12232937 | L7: 22000000 | M7: {=_xlfn.XLOOKUP(A7,Sheet2!$A$1:$A$3726,Sheet2!$B$1:$G$3726)} -> 40137 | N7: Color | O7: Action | P7: English | Q7: USA | R7: PG-13
A8: 12 Years a Slave | B8: QuvenzhanÃ© Wallis | C8: Steve McQueen | D8: 2000 | E8: 4251 | F8: 0 | G8: 83000 | H8: 8.1 | I8: 597 | J8: 134 | K8: 56667870 | L8: 20000000 | M8: {=_xlfn.XLOOKUP(A8,Sheet2!$A$1:$A$3726,Sheet2!$B$1:$G$3726)} -> 41587 | N8: Color | O8: Biography | P8: English | Q8: USA | R8: R
A9: 127 Hours | B9: James Franco | C9: Danny Boyle | D9: 11000 | E9: 11984 | F9: 0 | G9: 63000 | H9: 7.6 | I9: 450 | J9: 94 | K9: 18329466 | L9: 18000000 | M9: {=_xlfn.XLOOKUP(A9,Sheet2!$A$1:$A$3726,Sheet2!$B$1:$G$3726)} -> 40312 | N9: Color | O9: Adventure | P9: English | Q9: USA | R9: R
A10: 13 Going on 30 | B10: Jennifer Garner | C10: Gary Winick | D10: 3000 | E10: 6742 | F10: 56 | G10: 0 | H10: 6.1 | I10: 119 | J10: 98 | K10: 56044241 | L10: 37000000 | M10: {=_xlfn.XLOOKUP(A10,Sheet2!$A$1:$A$3726,Sheet2!$B$1:$G$3726)} -> 38154 | N10: Color | O10: Comedy | P10: English | Q10: USA | R10: PG-13
A11: 1408 | B11: Drew Powell | C11: Mikael HÃ¥fstrÃ¶m | D11: 129 | E11: 214 | F11: 101 | G11: 11000 | H11: 6.8 | I11: 314 | J11: 114 | K11: 71975611 | L11: 25000000 | M11: {=_xlfn.XLOOKUP(A11,Sheet2!$A$1:$A$3726,Sheet2!$B$1:$G$3726)} -> 39152 | N11: Color | O11: Fantasy | P11: English | Q11: USA | R11: PG-13
A12: 15 Minutes | B12: Robert De Niro | C12: John Herzfeld | D12: 22000 | E12: 33585 | F12: 17 | G12: 748 | H12: 6.1 | I12: 151 | J12: 120 | K12: 24375436 | L12: 42000000 | M12: {=_xlfn.XLOOKUP(A12,Sheet2!$A$1:$A$3726,Sheet2!$B$1:$G$3726)} -> 36908 | N12: Color | O12: Action | P12: English | Q12: USA | R12: R
A13: 16 Blocks | B13: Bruce Willis | C13: Richard Donner | D13: 13000 | E13: 15053 | F13: 503 | G13: 0 | H13: 6.6 | I13: 199 | J13: 102 | K13: 36883539 | L13: 52000000 | M13: {=_xlfn.XLOOKUP(A13,Sheet2!$A$1:$A$3726,Sheet2!$B$1:$G$3726)} -> 39029 | N13: Color | O13: Action | P13: English | Q13: Germany | R13: PG-13
... A123: Abduction | B123: Ken Arnold | C123: John Singleton | D123: 327 | E123: 561 | F123: 309 | G123: 13000 | H123: 5 | I123: 180 | J123: 106 | K123: 28064226 | L123: 35000000 | M123: {=_xlfn.XLOOKUP(A123,Sheet2!$A$1:$A$3726,Sheet2!$B$1:$G$3726)} -> 40642 | N123: Color | O123: Action | P123: English | Q123: USA | R123: PG-13
A124: Aberdeen | B124: Charlotte Rampling | C124: Hans Petter Moland | D124: 844 | E124: 846 | F124: 19 | G124: 260 | H124: 7.3 | I124: 28 | J124: 106 | K124: 64148 | L124: 6500000 | M124: {=_xlfn.XLOOKUP(A124,Sheet2!$A$1:$A$3726,Sheet2!$B$1:$G$3726)} -> 36567 | N124: Color | O124: Drama | P124: English | Q124: UK | R124: 0
A125: About a Boy | B125: Sharon Small | C125: Chris Weitz | D125: 66 | E125: 74 | F125: 129 | G125: 0 | H125: 7.1 | I125: 158 | J125: 101 | K125: 40566655 | L125: 30000000 | M125: {=_xlfn.XLOOKUP(A125,Sheet2!$A$1:$A$3726,Sheet2!$B$1:$G$3726)} -> 37424 | N125: Color | O125: Comedy | P125: English | Q125: UK | R125: PG-13
A126: About Last Night | B126: Joe Lo Truglio | C126: Steve Pink | D126: 833 | E126: 2800 | F126: 38 | G126: 0 | H126: 6.1 | I126: 90 | J126: 100 | K126: 48637684 | L126: 12500000 | M126: {=_xlfn.XLOOKUP(A126,Sheet2!$A$1:$A$3726,Sheet2!$B$1:$G$3726)} -> 41713 | N126: Color | O126: Comedy | P126: English | Q126: USA | R126: R
A127: About Schmidt | B127: Hope Davis | C127: Alexander Payne | D127: 442 | E127: 1556 | F127: 729 | G127: 0 | H127: 7.2 | I127: 217 | J127: 125 | K127: 65010106 | L127: 30000000 | M127: {=_xlfn.XLOOKUP(A127,Sheet2!$A$1:$A$3726,Sheet2!$B$1:$G$3726)} -> 37405 | N127: Color | O127: Comedy | P127: English | Q127: USA | R127: R
A128: About Time | B128: Tom Hughes | C128: Richard Curtis | D128: 565 | E128: 1595 | F128: 628 | G128: 105000 | H128: 7.8 | I128: 274 | J128: 123 | K128: 15294553 | L128: 12000000 | M128: {=_xlfn.XLOOKUP(A128,Sheet2!$A$1:$A$3726,Sheet2!$B$1:$G$3726)} -> 41385 | N128: Color | O128: Drama | P128: English | Q128: UK | R128: R
A129: Abraham Lincoln: Vampire Hunter | B129: Rufus Sewell | C129: Timur Bekmambetov | D129: 3000 | E129: 8281 | F129: 335 | G129: 98000 | H129: 5.9 | I129: 393 | J129: 105 | K129: 37516013 | L129: 69000000 | M129: {=_xlfn.XLOOKUP(A129,Sheet2!$A$1:$A$3726,Sheet2!$B$1:$G$3726)} -> 41168 | N129: Color | O129: Action | P129: English | Q129: USA | R129: R
A130: Absolute Power | B130: Clint Eastwood | C130: Clint Eastwood | D130: 16000 | E130: 19139 | F130: 16000 | G130: 1000 | H130: 6.7 | I130: 76 | J130: 121 | K130: 50007168 | L130: 50000000 | M130: {=_xlfn.XLOOKUP(A130,Sheet2!$A$1:$A$3726,Sheet2!$B$1:$G$3726)} -> 35763 | N130: Color | O130: Action | P130: English | Q130: USA | R130: R
A131: Ace Ventura: Pet Detective | B131: Sean Young | C131: Tom Shadyac | D131: 759 | E131: 2462 | F131: 293 | G131: 0 | H131: 6.9 | I131: 61 | J131: 78 | K131: 72217000 | L131: 12000000 | M131: {=_xlfn.XLOOKUP(A131,Sheet2!$A$1:$A$3726,Sheet2!$B$1:$G$3726)} -> 34608 | N131: Color | O131: Comedy | P131: English | Q131: USA | R131: PG-13
A132: Ace Ventura: When Nature Calls | B132: Bruce Spence | C132: Steve Oedekerk | D132: 531 | E132: 2203 | F132: 176 | G132: 0 | H132: 6.3 | I132: 59 | J132: 90 | K132: 108360000 | L132: 30000000 | M132: {=_xlfn.XLOOKUP(A132,Sheet2!$A$1:$A$3726,Sheet2!$B$1:$G$3726)} -> 34981 | N132: Color | O132: Adventure | P132: English | Q132: USA | R132: PG-13
A133: Across the Universe | B133: Jim Sturgess | C133: Julie Taymor | D133: 5000 | E133: 5405 | F133: 278 | G133: 14000 | H133: 7.4 | I133: 156 | J133: 133 | K133: 24343673 | L133: 45000000 | M133: {=_xlfn.XLOOKUP(A133,Sheet2!$A$1:$A$3726,Sheet2!$B$1:$G$3726)} -> 39274 | N133: Color | O133: Drama | P133: English | Q133: USA | R133: PG-13
A134: Act of Valor | B134: Alex Veadov | C134: Mike McCoy | D134: 93 | E134: 146 | F134: 16 | G134: 15000 | H134: 6.5 | I134: 216 | J134: 110 | K134: 70011073 | L134: 12000000 | M134: {=_xlfn.XLOOKUP(A134,Sheet2!$A$1:$A$3726,Sheet2!$B$1:$G$3726)} -> 41194 | N134: Color | O134: Action | P134: English | Q134: USA | R134: R
A135: Action Jackson | B135: Bill Duke | C135: Craig R. Baxley | D135: 1000 | E135: 5282 | F135: 22 | G135: 978 | H135: 5.2 | I135: 35 | J135: 96 | K135: 20257000 | L135: 7000000 | M135: {=_xlfn.XLOOKUP(A135,Sheet2!$A$1:$A$3726,Sheet2!$B$1:$G$3726)} -> 32333 | N135: Color | O135: Action | P135: English | Q135: USA | R135: R
A136: Adaptation. | B136: Nicolas Cage | C136: Spike Jonze | D136: 12000 | E136: 25489 | F136: 0 | G136: 0 | H136: 7.7 | I136: 241 | J136: 81 | K136: 22245861 | L136: 19000000 | M136: {=_xlfn.XLOOKUP(A136,Sheet2!$A$1:$A$3726,Sheet2!$B$1:$G$3726)} -> 37359 | N136: Color | O136: Comedy | P136: English | Q136: USA | R136: R
... A146: Agora | B146: Max Minghella | C146: Alejandro AmenÃ¡bar | D146: 614 | E146: 1829 | F146: 448 | G146: 29000 | H146: 7.2 | I146: 180 | J146: 141 | K146: 617840 | L146: 70000000 | M146: {=_xlfn.XLOOKUP(A146,Sheet2!$A$1:$A$3726,Sheet2!$B$1:$G$3726)} -> 39874 | N146: Color | O146: Adventure | P146: English | Q146: Spain | R146: R
A147: Aimee & Jaguar | B147: Heike Makatsch | C147: Max FÃ¤rberbÃ¶ck | D147: 177 | E147: 333 | F147: 4 | G147: 687 | H147: 7.3 | I147: 63 | J147: 125 | K147: 927107 | L147: 15000000 | M147: {=_xlfn.XLOOKUP(A147,Sheet2!$A$1:$A$3726,Sheet2!$B$1:$G$3726)} -> 36455 | N147: Color | O147: Biography | P147: German | Q147: Germany | R147: 0
A148: Air Bud | B148: Kevin Zegers | C148: Charles Martin Smith | D148: 2000 | E148: 4277 | F148: 188 | G148: 902 | H148: 5.1 | I148: 35 | J148: 98 | K148: 24629916 | L148: 3000000 | M148: {=_xlfn.XLOOKUP(A148,Sheet2!$A$1:$A$3726,Sheet2!$B$1:$G$3726)} -> 35717 | N148: Color | O148: Comedy | P148: English | Q148: USA | R148: PG
A149: Air Force One | B149: Harrison Ford | C149: Wolfgang Petersen | D149: 11000 | E149: 23603 | F149: 249 | G149: 0 | H149: 6.4 | I149: 142 | J149: 124 | K149: 172620724 | L149: 85000000 | M149: {=_xlfn.XLOOKUP(A149,Sheet2!$A$1:$A$3726,Sheet2!$B$1:$G$3726)} -> 35541 | N149: Color | O149: Action | P149: English | Q149: USA | R149: R
A150: Airborne | B150: Alanna Ubach | C150: Rob Bowman | D150: 584 | E150: 1218 | F150: 38 | G150: 0 | H150: 6.2 | I150: 9 | J150: 91 | K150: 2850263 | L150: 2600000 | M150: {=_xlfn.XLOOKUP(A150,Sheet2!$A$1:$A$3726,Sheet2!$B$1:$G$3726)} -> 34221 | N150: Color | O150: Adventure | P150: English | Q150: USA | R150: PG
A151: Airplane! | B151: Peter Graves | C151: Jim Abrahams | D151: 628 | E151: 2726 | F151: 104 | G151: 16000 | H151: 7.8 | I151: 134 | J151: 88 | K151: 83400000 | L151: 3500000 | M151: {=_xlfn.XLOOKUP(A151,Sheet2!$A$1:$A$3726,Sheet2!$B$1:$G$3726)} -> 29411 | N151: Color | O151: Comedy | P151: English | Q151: USA | R151: PG
A152: Akira | B152: Mitsuo Iwata | C152: Katsuhiro Ã”tomo | D152: 6 | E152: 28 | F152: 78 | G152: 0 | H152: 8.1 | I152: 150 | J152: 124 | K152: 439162 | L152: 1100000000 | M152: {=_xlfn.XLOOKUP(A152,Sheet2!$A$1:$A$3726,Sheet2!$B$1:$G$3726)} -> 32491 | N152: Color | O152: Action | P152: Japanese | Q152: Japan | R152: R
A153: Aladdin | B153: Robin Williams | C153: Ron Clements | D153: 49000 | E153: 52970 | F153: 63 | G153: 0 | H153: 8 | I153: 124 | J153: 90 | K153: 217350219 | L153: 28000000 | M153: {=_xlfn.XLOOKUP(A153,Sheet2!$A$1:$A$3726,Sheet2!$B$1:$G$3726)} -> 33910 | N153: Color | O153: Adventure | P153: English | Q153: USA | R153: G
A154: Albert Nobbs | B154: Mia Wasikowska | C154: Rodrigo GarcÃ­a | D154: 3000 | E154: 4370 | F154: 127 | G154: 0 | H154: 6.7 | I154: 222 | J154: 113 | K154: 3014541 | L154: 8000000 | M154: {=_xlfn.XLOOKUP(A154,Sheet2!$A$1:$A$3726,Sheet2!$B$1:$G$3726)} -> 40558 | N154: Color | O154: Drama | P154: English | Q154: UK | R154: R
A155: Albino Alligator | B155: Viggo Mortensen | C155: Kevin Spacey | D155: 10000 | E155: 13718 | F155: 18000 | G155: 225 | H155: 6.1 | I155: 37 | J155: 97 | K155: 326308 | L155: 5000000 | M155: {=_xlfn.XLOOKUP(A155,Sheet2!$A$1:$A$3726,Sheet2!$B$1:$G$3726)} -> 35428 | N155: Color | O155: Crime | P155: English | Q155: USA | R155: R
A156: Alex & Emma | B156: David Paymer | C156: Rob Reiner | D156: 372 | E156: 977 | F156: 0 | G156: 625 | H156: 5.6 | I156: 73 | J156: 96 | K156: 14208384 | L156: 30000000 | M156: {=_xlfn.XLOOKUP(A156,Sheet2!$A$1:$A$3726,Sheet2!$B$1:$G$3726)} -> 37798 | N156: Color | O156: Comedy | P156: English | Q156: USA | R156: PG-13
A157: Alex Cross | B157: Cicely Tyson | C157: Rob Cohen | D157: 907 | E157: 2471 | F157: 357 | G157: 11000 | H157: 5.1 | I157: 211 | J157: 101 | K157: 25863915 | L157: 35000000 | M157: {=_xlfn.XLOOKUP(A157,Sheet2!$A$1:$A$3726,Sheet2!$B$1:$G$3726)} -> 41154 | N157: Color | O157: Action | P157: English | Q157: USA | R157: PG-13
A158: Alex Rider: Operation Stormbreaker | B158: Alex Pettyfer | C158: Geoffrey Sax | D158: 15000 | E158: 15638 | F158: 13 | G158: 823 | H158: 5.1 | I158: 66 | J158: 93 | K158: 652526 | L158: 40000000 | M158: {=_xlfn.XLOOKUP(A158,Sheet2!$A$1:$A$3726,Sheet2!$B$1:$G$3726)} -> 38793 | N158: Color | O158: Action | P158: English | Q158: Germany | R158: PG
A159: Alexander | B159: Anthony Hopkins | C159: Oliver Stone | D159: 12000 | E159: 24598 | F159: 0 | G159: 0 | H159: 5.5 | I159: 248 | J159: 206 | K159: 34293771 | L159: 155000000 | M159: {=_xlfn.XLOOKUP(A159,Sheet2!$A$1:$A$3726,Sheet2!$B$1:$G$3726)} -> 38110 | N159: Color | O159: Action | P159: English | Q159: Germany | R159: R
... A162: Ali | B162: Will Smith | C162: Michael Mann | D162: 10000 | E162: 14196 | F162: 0 | G162: 0 | H162: 6.8 | I162: 174 | J162: 165 | K162: 58183966 | L162: 107000000 | M162: {=_xlfn.XLOOKUP(A162,Sheet2!$A$1:$A$3726,Sheet2!$B$1:$G$3726)} -> 37172 | N162: Black and White | O162: Biography | P162: English | Q162: USA | R162: R
A163: Alias Betty | B163: Sandrine Kiberlain | C163: Claude Miller | D163: 71 | E163: 262 | F163: 27 | G163: 26 | H163: 6.9 | I163: 38 | J163: 103 | K163: 206400 | L163: 50000000 | M163: {=_xlfn.XLOOKUP(A163,Sheet2!$A$1:$A$3726,Sheet2!$B$1:$G$3726)} -> 37005 | N163: Color | O163: Comedy | P163: French | Q163: France | R163: 0
A164: Alice in Wonderland | B164: Johnny Depp | C164: Tim Burton | D164: 40000 | E164: 79957 | F164: 13000 | G164: 24000 | H164: 6.5 | I164: 451 | J164: 108 | K164: 334185206 | L164: 200000000 | M164: {=_xlfn.XLOOKUP(A164,Sheet2!$A$1:$A$3726,Sheet2!$B$1:$G$3726)} -> 40266 | N164: Color | O164: Adventure | P164: English | Q164: USA | R164: PG
A165: Alien | B165: Tom Skerritt | C165: Ridley Scott | D165: 1000 | E165: 2524 | F165: 0 | G165: 23000 | H165: 8.5 | I165: 392 | J165: 116 | K165: 78900000 | L165: 11000000 | M165: {=_xlfn.XLOOKUP(A165,Sheet2!$A$1:$A$3726,Sheet2!$B$1:$G$3726)} -> 29131 | N165: Color | O165: Horror | P165: English | Q165: UK | R165: R
A166: Alien 3 | B166: Charles S. Dutton | C166: David Fincher | D166: 534 | E166: 1543 | F166: 21000 | G166: 0 | H166: 6.4 | I166: 210 | J166: 145 | K166: 55473600 | L166: 50000000 | M166: {=_xlfn.XLOOKUP(A166,Sheet2!$A$1:$A$3726,Sheet2!$B$1:$G$3726)} -> 33950 | N166: Color | O166: Action | P166: English | Q166: USA | R166: R
A167: Alien: Resurrection | B167: Gary Dourdan | C167: Jean-Pierre Jeunet | D167: 1000 | E167: 3090 | F167: 0 | G167: 0 | H167: 6.3 | I167: 223 | J167: 116 | K167: 47748610 | L167: 75000000 | M167: {=_xlfn.XLOOKUP(A167,Sheet2!$A$1:$A$3726,Sheet2!$B$1:$G$3726)} -> 35466 | N167: Color | O167: Action | P167: English | Q167: USA | R167: R
A168: Aliens | B168: Michael Biehn | C168: James Cameron | D168: 2000 | E168: 4228 | F168: 0 | G168: 18000 | H168: 8.4 | I168: 250 | J168: 154 | K168: 85200000 | L168: 18500000 | M168: {=_xlfn.XLOOKUP(A168,Sheet2!$A$1:$A$3726,Sheet2!$B$1:$G$3726)} -> 31619 | N168: Color | O168: Action | P168: English | Q168: USA | R168: R
A169: Aliens in the Attic | B169: Malese Jow | C169: John Schultz | D169: 1000 | E169: 3423 | F169: 13 | G169: 916 | H169: 5.4 | I169: 82 | J169: 86 | K169: 25200412 | L169: 45000000 | M169: {=_xlfn.XLOOKUP(A169,Sheet2!$A$1:$A$3726,Sheet2!$B$1:$G$3726)} -> 39967 | N169: Color | O169: Adventure | P169: English | Q169: USA | R169: PG
A170: Aliens vs. Predator: Requiem | B170: Sam Trammell | C170: Colin Strause | D170: 1000 | E170: 4324 | F170: 25 | G170: 0 | H170: 4.7 | I170: 211 | J170: 102 | K170: 41797066 | L170: 40000000 | M170: {=_xlfn.XLOOKUP(A170,Sheet2!$A$1:$A$3726,Sheet2!$B$1:$G$3726)} -> 39249 | N170: Color | O170: Action | P170: English | Q170: USA | R170: R
A171: Alive | B171: Illeana Douglas | C171: Frank Marshall | D171: 344 | E171: 2054 | F171: 155 | G171: 0 | H171: 7.1 | I171: 43 | J171: 120 | K171: 36733909 | L171: 32000000 | M171: {=_xlfn.XLOOKUP(A171,Sheet2!$A$1:$A$3726,Sheet2!$B$1:$G$3726)} -> 34162 | N171: Color | O171: Adventure | P171: English | Q171: USA | R171: R
A172: All About Steve | B172: Bradley Cooper | C172: Phil Traill | D172: 14000 | E172: 16461 | F172: 3 | G172: 0 | H172: 4.8 | I172: 128 | J172: 99 | K172: 33860010 | L172: 15000000 | M172: {=_xlfn.XLOOKUP(A172,Sheet2!$A$1:$A$3726,Sheet2!$B$1:$G$3726)} -> 40034 | N172: Color | O172: Comedy | P172: English | Q172: USA | R172: PG-13
A173: All About the Benjamins | B173: Mike Epps | C173: Kevin Bray | D173: 706 | E173: 1421 | F173: 10 | G173: 530 | H173: 5.7 | I173: 40 | J173: 95 | K173: 25482931 | L173: 14000000 | M173: {=_xlfn.XLOOKUP(A173,Sheet2!$A$1:$A$3726,Sheet2!$B$1:$G$3726)} -> 37539 | N173: Color | O173: Action | P173: English | Q173: USA | R173: R
A174: All Is Lost | B174: Robert Redford | C174: J.C. Chandor | D174: 0 | E174: 0 | F174: 78 | G174: 18000 | H174: 6.9 | I174: 346 | J174: 106 | K174: 6262942 | L174: 9000000 | M174: {=_xlfn.XLOOKUP(A174,Sheet2!$A$1:$A$3726,Sheet2!$B$1:$G$3726)} -> 41467 | N174: Color | O174: Action | P174: English | Q174: USA | R174: PG-13
A175: All or Nothing | B175: Lesley Manville | C175: Mike Leigh | D175: 149 | E175: 251 | F175: 608 | G175: 484 | H175: 7.6 | I175: 81 | J175: 121 | K175: 112935 | L175: 9000000 | M175: {=_xlfn.XLOOKUP(A175,Sheet2!$A$1:$A$3726,Sheet2!$B$1:$G$3726)} -> 37438 | N175: Color | O175: Drama | P175: English | Q175: UK | R175: R
... A244: Another Year | B244: Jim Broadbent | C244: Mike Leigh | D244: 1000 | E244: 2265 | F244: 608 | G244: 0 | H244: 7.3 | I244: 248 | J244: 129 | K244: 3205244 | L244: 10000000 | M244: {=_xlfn.XLOOKUP(A244,Sheet2!$A$1:$A$3726,Sheet2!$B$1:$G$3726)} -> 40446 | N244: Color | O244: Comedy | P244: English | Q244: UK | R244: PG-13
A245: Antarctic Edge: 70Â° South | B245: Naderev Sano | C245: Dena Seidel | D245: 0 | E245: 0 | F245: 0 | G245: 215 | H245: 7 | I245: 5 | J245: 72 | K245: 4914 | L245: 150000 | M245: {=_xlfn.XLOOKUP(A245,Sheet2!$A$1:$A$3726,Sheet2!$B$1:$G$3726)} -> 42057 | N245: Color | O245: Adventure | P245: English | Q245: USA | R245: 0
A246: Antarctica: A Year on Ice | B246: Josh Swanson | C246: Anthony Powell | D246: 53 | E246: 86 | F246: 9 | G246: 0 | H246: 7.6 | I246: 31 | J246: 91 | K246: 287761 | L246: 1000000 | M246: {=_xlfn.XLOOKUP(A246,Sheet2!$A$1:$A$3726,Sheet2!$B$1:$G$3726)} -> 41385 | N246: Color | O246: Adventure | P246: English | Q246: New Zealand | R246: PG
A247: Antitrust | B247: Tyler Labine | C247: Peter Howitt | D247: 779 | E247: 1297 | F247: 29 | G247: 0 | H247: 6.1 | I247: 123 | J247: 109 | K247: 10965209 | L247: 30000000 | M247: {=_xlfn.XLOOKUP(A247,Sheet2!$A$1:$A$3726,Sheet2!$B$1:$G$3726)} -> 36914 | N247: Color | O247: Action | P247: English | Q247: USA | R247: PG-13
A248: Ant-Man | B248: Judy Greer | C248: Peyton Reed | D248: 2000 | E248: 5730 | F248: 235 | G248: 61000 | H248: 7.4 | I248: 517 | J248: 117 | K248: 180191634 | L248: 130000000 | M248: {=_xlfn.XLOOKUP(A248,Sheet2!$A$1:$A$3726,Sheet2!$B$1:$G$3726)} -> 42040 | N248: Color | O248: Action | P248: English | Q248: USA | R248: PG-13
A249: Antwone Fisher | B249: Denzel Washington | C249: Denzel Washington | D249: 18000 | E249: 20456 | F249: 18000 | G249: 0 | H249: 7.3 | I249: 121 | J249: 117 | K249: 21078145 | L249: 12500000 | M249: {=_xlfn.XLOOKUP(A249,Sheet2!$A$1:$A$3726,Sheet2!$B$1:$G$3726)} -> 37526 | N249: Color | O249: Biography | P249: English | Q249: USA | R249: PG-13
A250: Antz | B250: Sylvester Stallone | C250: Eric Darnell | D250: 13000 | E250: 25788 | F250: 35 | G250: 0 | H250: 6.6 | I250: 131 | J250: 83 | K250: 90646554 | L250: 105000000 | M250: {=_xlfn.XLOOKUP(A250,Sheet2!$A$1:$A$3726,Sheet2!$B$1:$G$3726)} -> 36046 | N250: Color | O250: Adventure | P250: English | Q250: USA | R250: PG
A251: Any Given Sunday | B251: Al Pacino | C251: Oliver Stone | D251: 14000 | E251: 20761 | F251: 0 | G251: 0 | H251: 6.8 | I251: 171 | J251: 156 | K251: 75530832 | L251: 55000000 | M251: {=_xlfn.XLOOKUP(A251,Sheet2!$A$1:$A$3726,Sheet2!$B$1:$G$3726)} -> 36333 | N251: Color | O251: Drama | P251: English | Q251: USA | R251: R
A252: Anything Else | B252: Woody Allen | C252: Woody Allen | D252: 11000 | E252: 14843 | F252: 11000 | G252: 827 | H252: 6.4 | I252: 128 | J252: 108 | K252: 3203044 | L252: 18000000 | M252: {=_xlfn.XLOOKUP(A252,Sheet2!$A$1:$A$3726,Sheet2!$B$1:$G$3726)} -> 37872 | N252: Color | O252: Comedy | P252: English | Q252: USA | R252: R
A253: Anywhere But Here | B253: Natalie Portman | C253: Wayne Wang | D253: 20000 | E253: 22040 | F253: 61 | G253: 638 | H253: 6.1 | I253: 36 | J253: 114 | K253: 18653615 | L253: 23000000 | M253: {=_xlfn.XLOOKUP(A253,Sheet2!$A$1:$A$3726,Sheet2!$B$1:$G$3726)} -> 36287 | N253: Color | O253: Comedy | P253: English | Q253: USA | R253: PG-13
A254: Apocalypse Now | B254: Harrison Ford | C254: Francis Ford Coppola | D254: 11000 | E254: 25313 | F254: 0 | G254: 19000 | H254: 8.5 | I254: 261 | J254: 289 | K254: 78800000 | L254: 31500000 | M254: {=_xlfn.XLOOKUP(A254,Sheet2!$A$1:$A$3726,Sheet2!$B$1:$G$3726)} -> 29106 | N254: Color | O254: Drama | P254: English | Q254: USA | R254: R
A255: Apocalypto | B255: Rudy Youngblood | C255: Mel Gibson | D255: 708 | E255: 848 | F255: 0 | G255: 14000 | H255: 7.8 | I255: 283 | J255: 139 | K255: 50859889 | L255: 40000000 | M255: {=_xlfn.XLOOKUP(A255,Sheet2!$A$1:$A$3726,Sheet2!$B$1:$G$3726)} -> 38850 | N255: Color | O255: Action | P255: Maya | Q255: USA | R255: R
A256: Apollo 13 | B256: Tom Hanks | C256: Ron Howard | D256: 15000 | E256: 17171 | F256: 2000 | G256: 5000 | H256: 7.6 | I256: 159 | J256: 140 | K256: 172071312 | L256: 62000000 | M256: {=_xlfn.XLOOKUP(A256,Sheet2!$A$1:$A$3726,Sheet2!$B$1:$G$3726)} -> 34940 | N256: Color | O256: Adventure | P256: English | Q256: USA | R256: PG
A257: Apollo 18 | B257: Warren Christie | C257: Gonzalo LÃ³pez-Gallego | D257: 520 | E257: 1520 | F257: 17 | G257: 0 | H257: 5.2 | I257: 228 | J257: 86 | K257: 17683670 | L257: 5000000 | M257: {=_xlfn.XLOOKUP(A257,Sheet2!$A$1:$A$3726,Sheet2!$B$1:$G$3726)} -> 40773 | N257: Color | O257: Horror | P257: English | Q257: USA | R257: PG-13
... A268: Army of Darkness | B268: Patricia Tallman | C268: Sam Raimi | D268: 901 | E268: 3913 | F268: 0 | G268: 10000 | H268: 7.6 | I268: 221 | J268: 88 | K268: 11501093 | L268: 13000000 | M268: {=_xlfn.XLOOKUP(A268,Sheet2!$A$1:$A$3726,Sheet2!$B$1:$G$3726)} -> 33605 | N268: Color | O268: Comedy | P268: English | Q268: USA | R268: R
A269: Arnolds Park | B269: Kendyl Joi | C269: Gene Teigland | D269: 23 | E269: 85 | F269: 0 | G269: 11 | H269: 5.6 | J269: 103 | K269: 23616 | L269: 600000 | M269: {=_xlfn.XLOOKUP(A269,Sheet2!$A$1:$A$3726,Sheet2!$B$1:$G$3726)} -> 39322 | N269: Color | O269: Mystery | P269: English | Q269: USA | R269: PG-13
A270: Around the World in 80 Days | B270: Jim Broadbent | C270: Frank Coraci | D270: 1000 | E270: 3175 | F270: 153 | G270: 0 | H270: 5.8 | I270: 188 | J270: 120 | K270: 24004159 | L270: 110000000 | M270: {=_xlfn.XLOOKUP(A270,Sheet2!$A$1:$A$3726,Sheet2!$B$1:$G$3726)} -> 38020 | N270: Color | O270: Action | P270: English | Q270: USA | R270: PG
A271: Arthur and the Invisibles | B271: Mia Farrow | C271: Luc Besson | D271: 563 | E271: 683 | F271: 0 | G271: 941 | H271: 6 | I271: 101 | J271: 94 | K271: 15131330 | L271: 86000000 | M271: {=_xlfn.XLOOKUP(A271,Sheet2!$A$1:$A$3726,Sheet2!$B$1:$G$3726)} -> 39041 | N271: Color | O271: Adventure | P271: English | Q271: France | R271: PG
A272: Arthur Christmas | B272: Jim Broadbent | C272: Sarah Smith | D272: 1000 | E272: 2707 | F272: 6 | G272: 0 | H272: 7.1 | I272: 190 | J272: 97 | K272: 46440491 | L272: 100000000 | M272: {=_xlfn.XLOOKUP(A272,Sheet2!$A$1:$A$3726,Sheet2!$B$1:$G$3726)} -> 40761 | N272: Color | O272: Adventure | P272: English | Q272: UK | R272: PG
A273: As Above, So Below | B273: Ben Feldman | C273: John Erick Dowdle | D273: 1000 | E273: 1410 | F273: 66 | G273: 14000 | H273: 6.1 | I273: 196 | J273: 93 | K273: 21197315 | L273: 5000000 | M273: {=_xlfn.XLOOKUP(A273,Sheet2!$A$1:$A$3726,Sheet2!$B$1:$G$3726)} -> 41977 | N273: Color | O273: Horror | P273: English | Q273: USA | R273: R
A274: As Good as It Gets | B274: Lupe Ontiveros | C274: James L. Brooks | D274: 625 | E274: 1474 | F274: 274 | G274: 11000 | H274: 7.7 | I274: 156 | J274: 139 | K274: 147637474 | L274: 50000000 | M274: {=_xlfn.XLOOKUP(A274,Sheet2!$A$1:$A$3726,Sheet2!$B$1:$G$3726)} -> 35778 | N274: Color | O274: Comedy | P274: English | Q274: USA | R274: PG-13
A275: As It Is in Heaven | B275: Michael Nyqvist | C275: Kay Pollak | D275: 690 | E275: 774 | F275: 10 | G275: 0 | H275: 7.6 | I275: 34 | J275: 133 | K275: 9910 | L275: 25000000 | M275: {=_xlfn.XLOOKUP(A275,Sheet2!$A$1:$A$3726,Sheet2!$B$1:$G$3726)} -> 38117 | N275: Color | O275: Comedy | P275: Swedish | Q275: Sweden | R275: 0
A276: Assassins | B276: Muse Watson | C276: Richard Donner | D276: 45000 | E276: 58528 | F276: 503 | G276: 0 | H276: 6.3 | I276: 61 | J276: 132 | K276: 30306268 | L276: 50000000 | M276: {=_xlfn.XLOOKUP(A276,Sheet2!$A$1:$A$3726,Sheet2!$B$1:$G$3726)} -> 34751 | N276: Black and White | O276: Action | P276: English | Q276: France | R276: R
A277: Assault on Precinct 13 | B277: Brian Dennehy | C277: Jean-FranÃ§ois Richet | D277: 954 | E277: 3148 | F277: 25 | G277: 999 | H277: 6.3 | I277: 152 | J277: 109 | K277: 19976073 | L277: 20000000 | M277: {=_xlfn.XLOOKUP(A277,Sheet2!$A$1:$A$3726,Sheet2!$B$1:$G$3726)} -> 38390 | N277: Color | O277: Action | P277: English | Q277: USA | R277: R
A278: Astro Boy | B278: Nicolas Cage | C278: David Bowers | D278: 12000 | E278: 23365 | F278: 42 | G278: 0 | H278: 6.3 | I278: 138 | J278: 94 | K278: 19548064 | L278: 65000000 | M278: {=_xlfn.XLOOKUP(A278,Sheet2!$A$1:$A$3726,Sheet2!$B$1:$G$3726)} -> 39881 | N278: Color | O278: Action | P278: English | Q278: Hong Kong | R278: PG
A279: At First Sight | B279: Mira Sorvino | C279: Irwin Winkler | D279: 978 | E279: 3821 | F279: 34 | G279: 0 | H279: 5.9 | I279: 55 | J279: 128 | K279: 22326247 | L279: 60000000 | M279: {=_xlfn.XLOOKUP(A279,Sheet2!$A$1:$A$3726,Sheet2!$B$1:$G$3726)} -> 36284 | N279: Black and White | O279: Drama | P279: English | Q279: USA | R279: PG-13
A280: Atlantis: The Lost Empire | B280: Leonard Nimoy | C280: Gary Trousdale | D280: 12000 | E280: 15237 | F280: 21 | G280: 0 | H280: 6.8 | I280: 146 | J280: 95 | K280: 84037039 | L280: 120000000 | M280: {=_xlfn.XLOOKUP(A280,Sheet2!$A$1:$A$3726,Sheet2!$B$1:$G$3726)} -> 37085 | N280: Color | O280: Action | P280: English | Q280: USA | R280: PG
A281: Atlas Shrugged II: The Strike | B281: Robert Picardo | C281: John Putch | D281: 823 | E281: 5262 | F281: 60 | G281: 0 | H281: 5.5 | I281: 23 | J281: 111 | K281: 3333823 | L281: 10000000 | M281: {=_xlfn.XLOOKUP(A281,Sheet2!$A$1:$A$3726,Sheet2!$B$1:$G$3726)} -> 41026 | N281: Color | O281: Drama | P281: English | Q281: USA | R281: PG-13
A282: Atlas Shrugged: Who Is John Galt? | B282: Joaquim de Almeida | C282: James Manera | D282: 578 | E282: 3382 | F282: 0 | G282: 0 | H282: 4.4 | I282: 12 | J282: 99 | K282: 830210 | L282: 5000000 | M282: {=_xlfn.XLOOKUP(A282,Sheet2!$A$1:$A$3726,Sheet2!$B$1:$G$3726)} -> 41802 | N282: Color | O282: Drama | P282: English | Q282: USA | R282: PG-13
A283: Atonement | B283: Benedict Cumberbatch | C283: Joe Wright | D283: 19000 | E283: 20499 | F283: 456 | G283: 12000 | H283: 7.8 | I283: 316 | J283: 123 | K283: 50921738 | L283: 30000000 | M283: {=_xlfn.XLOOKUP(A283,Sheet2!$A$1:$A$3726,Sheet2!$B$1:$G$3726)} -> 39314 | N283: Color | O283: Drama | P283: English | Q283: UK | R283: R
A284: Attack the Block | B284: John Boyega | C284: Joe Cornish | D284: 1000 | E284: 2011 | F284: 115 | G284: 18000 | H284: 6.6 | I284: 399 | J284: 88 | K284: 1024175 | L284: 13000000 | M284: {=_xlfn.XLOOKUP(A284,Sheet2!$A$1:$A$3726,Sheet2!$B$1:$G$3726)} -> 40597 | N284: Color | O284: Action | P284: English | Q284: UK | R284: R
A285: August Rush | B285: Robin Williams | C285: Kirsten Sheridan | D285: 49000 | E285: 50927 | F285: 59 | G285: 18000 | H285: 7.5 | I285: 148 | J285: 114 | K285: 31655091 | L285: 30000000 | M285: {=_xlfn.XLOOKUP(A285,Sheet2!$A$1:$A$3726,Sheet2!$B$1:$G$3726)} -> 39161 | N285: Color | O285: Drama | P285: English | Q285: USA | R285: PG
A286: August: Osage County | B286: Benedict Cumberbatch | C286: John Wells | D286: 19000 | E286: 39690 | F286: 53 | G286: 30000 | H286: 7.3 | I286: 322 | J286: 121 | K286: 37738400 | L286: 25000000 | M286: {=_xlfn.XLOOKUP(A286,Sheet2!$A$1:$A$3726,Sheet2!$B$1:$G$3726)} -> 41409 | N286: Color | O286: Drama | P286: English | Q286: USA | R286: R
A287: Austin Powers in Goldmember | B287: Verne Troyer | C287: Jay Roach | D287: 645 | E287: 2725 | F287: 116 | G287: 0 | H287: 6.2 | I287: 194 | J287: 94 | K287: 213079163 | L287: 63000000 | M287: {=_xlfn.XLOOKUP(A287,Sheet2!$A$1:$A$3726,Sheet2!$B$1:$G$3726)} -> 37423 | N287: Color | O287: Action | P287: English | Q287: USA | R287: PG-13
... A297: Away We Go | B297: Catherine O'Hara | C297: Sam Mendes | D297: 925 | E297: 1997 | F297: 0 | G297: 7000 | H297: 7.1 | I297: 217 | J297: 98 | K297: 9430988 | L297: 17000000 | M297: {=_xlfn.XLOOKUP(A297,Sheet2!$A$1:$A$3726,Sheet2!$B$1:$G$3726)} -> 40118 | N297: Color | O297: Comedy | P297: English | Q297: USA | R297: R
A298: Ayurveda: Art of Being | C298: Pan Nalin | E298: 0 | F298: 95 | G298: 379 | H298: 7.6 | I298: 15 | J298: 102 | K298: 16892 | L298: 300000 | M298: {=_xlfn.XLOOKUP(A298,Sheet2!$A$1:$A$3726,Sheet2!$B$1:$G$3726)} -> 37138 | N298: Color | O298: Documentary | P298: English | Q298: India | R298: 0
A299: Baahubali: The Beginning | B299: Tamannaah Bhatia | C299: S.S. Rajamouli | D299: 218 | E299: 554 | F299: 50 | G299: 21000 | H299: 8.4 | I299: 44 | J299: 159 | K299: 6498000 | L299: 18026148 | M299: {=_xlfn.XLOOKUP(A299,Sheet2!$A$1:$A$3726,Sheet2!$B$1:$G$3726)} -> 42182 | N299: Color | O299: Action | P299: Telugu | Q299: India | R299: 0
A300: Babe | B300: Miriam Margolyes | C300: Chris Noonan | D300: 405 | E300: 1185 | F300: 108 | G300: 5000 | H300: 6.8 | I300: 79 | J300: 91 | K300: 66600000 | L300: 30000000 | M300: {=_xlfn.XLOOKUP(A300,Sheet2!$A$1:$A$3726,Sheet2!$B$1:$G$3726)} -> 34858 | N300: Color | O300: Comedy | P300: English | Q300: Australia | R300: G
A301: Babe: Pig in the City | B301: Adam Goldberg | C301: George Miller | D301: 1000 | E301: 2521 | F301: 750 | G301: 964 | H301: 5.8 | I301: 61 | J301: 97 | K301: 18318000 | L301: 80000000 | M301: {=_xlfn.XLOOKUP(A301,Sheet2!$A$1:$A$3726,Sheet2!$B$1:$G$3726)} -> 35864 | N301: Color | O301: Adventure | P301: English | Q301: Australia | R301: G
A302: Babel | B302: Brad Pitt | C302: Alejandro G. IÃ±Ã¡rritu | D302: 11000 | E302: 11248 | F302: 0 | G302: 0 | H302: 7.5 | I302: 285 | J302: 143 | K302: 34300771 | L302: 25000000 | M302: {=_xlfn.XLOOKUP(A302,Sheet2!$A$1:$A$3726,Sheet2!$B$1:$G$3726)} -> 38804 | N302: Color | O302: Drama | P302: English | Q302: France | R302: R
A303: Baby Boy | B303: Mo'Nique | C303: John Singleton | D303: 939 | E303: 3107 | F303: 309 | G303: 1000 | H303: 6.4 | I303: 41 | J303: 130 | K303: 28734552 | L303: 16000000 | M303: {=_xlfn.XLOOKUP(A303,Sheet2!$A$1:$A$3726,Sheet2!$B$1:$G$3726)} -> 37100 | N303: Black and White | O303: Crime | P303: English | Q303: USA | R303: R
A304: Baby Geniuses | B304: Kathleen Turner | C304: Bob Clark | D304: 899 | E304: 2936 | F304: 84 | G304: 0 | H304: 2.5 | I304: 45 | J304: 97 | K304: 27141959 | L304: 18000000 | M304: {=_xlfn.XLOOKUP(A304,Sheet2!$A$1:$A$3726,Sheet2!$B$1:$G$3726)} -> 36362 | N304: Color | O304: Comedy | P304: English | Q304: USA | R304: PG
A305: Baby Mama | B305: Tina Fey | C305: Michael McCullers | D305: 2000 | E305: 6930 | F305: 5 | G305: 0 | H305: 6 | I305: 145 | J305: 99 | K305: 60269340 | L305: 30000000 | M305: {=_xlfn.XLOOKUP(A305,Sheet2!$A$1:$A$3726,Sheet2!$B$1:$G$3726)} -> 39645 | N305: Color | O305: Comedy | P305: English | Q305: USA | R305: PG-13
A306: Babylon A.D. | B306: Vin Diesel | C306: Mathieu Kassovitz | D306: 14000 | E306: 15990 | F306: 326 | G306: 0 | H306: 5.6 | I306: 164 | J306: 101 | K306: 22531698 | L306: 70000000 | M306: {=_xlfn.XLOOKUP(A306,Sheet2!$A$1:$A$3726,Sheet2!$B$1:$G$3726)} -> 39601 | N306: Color | O306: Action | P306: English | Q306: France | R306: PG-13
A307: Baby's Day Out | B307: Joe Mantegna | C307: Patrick Read Johnson | D307: 1000 | E307: 2949 | F307: 32 | G307: 0 | H307: 5.9 | I307: 22 | J307: 99 | K307: 16671505 | L307: 50000000 | M307: {=_xlfn.XLOOKUP(A307,Sheet2!$A$1:$A$3726,Sheet2!$B$1:$G$3726)} -> 34530 | N307: Color | O307: Adventure | P307: English | Q307: USA | R307: PG
...

Sheet Sheet2
A1: Title | B1: Release Date | C1: Color/B&W | D1: Genre | E1: Language | F1: Country | G1: Rating
A2: Justin Bieber: Never Say Never | B2: 40795 | C2: Color | D2: Documentary | E2: English | F2: USA | G2: G
A3: Superbabies: Baby Geniuses 2 | B3: 37997 | C3: Color | D3: Comedy | E3: English | F3: Germany | G3: PG
A4: Disaster Movie | B4: 39500 | C4: Color | D4: Comedy | E4: English | F4: USA | G4: PG-13
A5: Who's Your Caddy? | B5: 39417 | C5: Color | D5: Comedy | E5: English | F5: USA | G5: PG-13
A6: Glitter | B6: 36928 | C6: Color | D6: Drama | E6: English | F6: USA | G6: PG-13
A7: From Justin to Kelly | B7: 37642 | C7: Color | D7: Comedy | E7: English | F7: USA | G7: PG
A8: Crossover | B8: 38816 | C8: Color | D8: Action | E8: English | F8: USA | G8: PG-13
A9: Son of the Mask | B9: 38368 | C9: Color | D9: Comedy | E9: English | F9: USA | G9: PG
A10: Chairman of the Board | B10: 35973 | C10: Color | D10: Comedy | E10: English | F10: USA | G10: PG-13
A11: Alone in the Dark | B11: 38455 | C11: Color | D11: Horror | E11: English | F11: Canada | G11: R
A12: Epic Movie | B12: 39362 | C12: Color | D12: Adventure | E12: English | F12: USA | G12: PG-13
A13: Gigli | B13: 37722 | C13: Color | D13: Comedy | E13: English | F13: USA | G13: R
... A35: Police Academy: Mission to Moscow | B35: 34520 | C35: Color | D35: Comedy | E35: English | F35: USA | G35: PG
A36: Neal 'N' Nikki | B36: 38661 | C36: Color | D36: Comedy | E36: English | F36: India
A37: Bucky Larson: Born to Be a Star | B37: 40727 | C37: Color | D37: Comedy | E37: English | F37: USA | G37: R
A38: Ocean's Eleven | B38: 37222 | C38: Color | D38: Crime | E38: English | F38: USA | G38: PG-13
A39: Catwoman | B39: 38290 | C39: Color | D39: Action | E39: English | F39: USA | G39: PG-13
A40: The Book of Mormon Movie, Volume 1: The Journey | B40: 37755 | C40: Color | D40: Adventure | E40: English | F40: USA | G40: PG-13
A41: Spice World | B41: 35445 | C41: Color | D41: Comedy | E41: English | F41: UK | G41: PG
A42: The Master of Disguise | B42: 37532 | C42: Color | D42: Comedy | E42: English | F42: USA | G42: PG
A43: Crossroads | B43: 37484 | C43: Color | D43: Comedy | E43: English | F43: USA | G43: PG-13
A44: Jack and Jill | B44: 40815 | C44: Color | D44: Comedy | E44: English | F44: USA | G44: PG
A45: Dumb and Dumberer: When Harry Met Lloyd | B45: 37839 | C45: Color | D45: Comedy | E45: English | F45: USA | G45: PG-13
A46: An Alan Smithee Film: Burn Hollywood Burn | B46: 35558 | C46: Color | D46: Comedy | E46: English | F46: USA | G46: R
A47: Megaforce | B47: 30012 | C47: Color | D47: Action | E47: English | F47: USA | G47: PG
A48: The Adventures of Sharkboy and Lavagirl 3-D | B48: 38546 | C48: Color | D48: Action | E48: English | F48: USA | G48: PG
... A215: Monkeybone | B215: 37044 | C215: Color | D215: Animation | E215: English | F215: USA | G215: PG-13
A216: Gory Gory Hallelujah | B216: 37952 | C216: Color | D216: Comedy | E216: English | F216: USA
A217: Turbulence | B217: 35451 | C217: Color | D217: Action | E217: English | F217: USA | G217: R
A218: Raise the Titanic | B218: 29480 | C218: Color | D218: Action | E218: English | F218: UK | G218: PG
A219: Jonah Hex | B219: 40260 | C219: Color | D219: Action | E219: English | F219: USA | G219: PG-13
A220: Did You Hear About the Morgans? | B220: 39960 | C220: Color | D220: Comedy | E220: English | F220: USA | G220: PG-13
A221: The Next Best Thing | B221: 36627 | C221: Color | D221: Comedy | E221: English | F221: USA | G221: PG-13
A222: Hanging Up | B222: 36859 | C222: Color | D222: Comedy | E222: English | F222: Germany | G222: PG-13
A223: The Musketeer | B223: 36935 | C223: Color | D223: Action | E223: English | F223: Germany | G223: PG-13
A224: The Marine | B224: 39059 | C224: Color | D224: Action | E224: English | F224: USA | G224: PG-13
A225: Pulse | B225: 38798 | C225: Color | D225: Drama | E225: English | F225: USA | G225: PG-13
A226: Aliens vs. Predator: Requiem | B226: 39249 | C226: Color | D226: Action | E226: English | F226: USA | G226: R
A227: Full Frontal | B227: 37344 | C227: Color | D227: Comedy | E227: English | F227: USA | G227: R
A228: Herbie Fully Loaded | B228: 38509 | C228: Color | D228: Adventure | E228: English | F228: USA | G228: G
... A235: DOA: Dead or Alive | B235: 38972 | C235: Color | D235: Action | E235: English | F235: USA | G235: PG-13
A236: Chocolate: Deep Dark Secrets | B236: 38425 | C236: Color | D236: Thriller | E236: Hindi | F236: India
A237: The Barbarians | B237: 32120 | C237: Color | D237: Adventure | E237: English | F237: USA | G237: R
A238: Supernova | B238: 36796 | C238: Color | D238: Horror | E238: English | F238: USA | G238: PG-13
A239: Knock Off | B239: 35868 | C239: Color | D239: Action | E239: English | F239: Aruba | G239: R
A240: Envy | B240: 38106 | C240: Color | D240: Comedy | E240: English | F240: USA | G240: PG-13
A241: The Spirit | B241: 39452 | C241: Color | D241: Action | E241: English | F241: USA | G241: PG-13
A242: Hoodwinked Too! Hood vs. Evil | B242: 40549 | C242: Color | D242: Animation | E242: English | F242: USA | G242: PG
A243: New York Minute | B243: 38177 | C243: Color | D243: Comedy | E243: English | F243: USA | G243: PG
A244: Elektra | B244: 38689 | C244: Color | D244: Action | E244: English | F244: Canada | G244: PG-13
A245: Godsend | B245: 38152 | C245: Color | D245: Drama | E245: English | F245: USA | G245: PG-13
A246: My Soul to Take | B246: 40476 | C246: Color | D246: Horror | E246: English | F246: USA | G246: R
A247: Lost Souls | B247: 36667 | C247: Color | D247: Drama | E247: English | F247: USA | G247: R
A248: Black Knight | B248: 37080 | C248: Color | D248: Adventure | E248: English | F248: USA | G248: PG-13
... A331: The Bridge of San Luis Rey | B331: 38241 | C331: Color | D331: Drama | E331: English | F331: UK | G331: PG
A332: Dil Jo Bhi Kahey... | B332: 38483 | C332: Color | D332: Romance | E332: English | F332: India
A333: The Green Mile | B333: 36376 | C333: Color | D333: Crime | E333: English | F333: USA | G333: R
A334: Alex Rider: Operation Stormbreaker | B334: 38793 | C334: Color | D334: Action | E334: English | F334: Germany | G334: PG
A335: Dylan Dog: Dead of Night | B335: 40383 | C335: Color | D335: Action | E335: English | F335: USA | G335: PG-13
A336: Not Cool | B336: 41649 | C336: Color | D336: Comedy | E336: English | F336: USA | G336: Not Rated
A337: Ransom | B337: 35132 | C337: Color | D337: Crime | E337: English | F337: USA | G337: R
A338: The Order | B338: 37738 | C338: Color | D338: Action | E338: English | F338: USA | G338: R
A339: The Scarlet Letter | B339: 34775 | C339: Color | D339: Drama | E339: English | F339: USA | G339: R
A340: Return to the Blue Lagoon | B340: 33544 | C340: Color | D340: Adventure | E340: English | F340: USA | G340: PG-13
A341: I, Frankenstein | B341: 41782 | C341: Color | D341: Action | E341: English | F341: Australia | G341: PG-13
A342: The Toxic Avenger Part II | B342: 32789 | C342: Color | D342: Action | E342: English | F342: USA | G342: R
A343: Get Carter | B343: 36849 | C343: Color | D343: Action | E343: English | F343: USA | G343: R
A344: Excessive Force | B344: 34169 | C344: Color | D344: Action | E344: English | F344: USA | G344: R
... A505: Mars Needs Moms | B505: 40709 | C505: Color | D505: Action | E505: English | F505: USA | G505: PG
A506: Ta Ra Rum Pum | B506: 39137 | C506: Color | D506: Comedy | E506: Hindi | F506: USA
A507: The Last Legion | B507: 39190 | C507: Color | D507: Action | E507: English | F507: UK | G507: PG-13
A508: Jupiter Ascending | B508: 42043 | C508: Color | D508: Action | E508: English | F508: USA | G508: PG-13
A509: The Guru | B509: 37386 | C509: Color | D509: Comedy | E509: English | F509: UK | G509: R
A510: A Simple Wish | B510: 35519 | C510: Color | D510: Comedy | E510: English | F510: USA | G510: PG
A511: Unfinished Business | B511: 42060 | C511: Color | D511: Comedy | E511: English | F511: USA | G511: R
A512: Play It to the Bone | B512: 36269 | C512: Color | D512: Comedy | E512: English | F512: USA | G512: R
A513: Bangkok Dangerous | B513: 39808 | C513: Color | D513: Action | E513: English | F513: USA | G513: R
A514: Under the Rainbow | B514: 29776 | C514: Color | D514: Comedy | E514: English | F514: USA | G514: PG
A515: Home on the Range | B515: 38015 | C515: Color | D515: Animation | E515: English | F515: USA | G515: PG
A516: I Spy | B516: 37561 | C516: Color | D516: Action | E516: English | F516: USA | G516: PG-13
A517: Man of the House | B517: 38508 | C517: Color | D517: Action | E517: English | F517: USA | G517: PG-13
A518: Land of the Lost | B518: 40141 | C518: Color | D518: Adventure | E518: English | F518: USA | G518: PG-13
... A826: Saint John of Las Vegas | B826: 39888 | C826: Color | D826: Comedy | E826: English | F826: USA | G826: R
A827: September Dawn | B827: 39397 | C827: Color | D827: Drama | F827: USA | G827: R
A828: Amigo | B828: 40218 | C828: Color | D828: Drama | E828: English | F828: USA | G828: R
A829: Mary Reilly | B829: 35070 | C829: Color | D829: Drama | E829: English | F829: USA | G829: R
A830: Just Visiting | B830: 36918 | C830: Color | D830: Comedy | E830: English | F830: France | G830: PG-13
A831: Rubber | B831: 40402 | C831: Color | D831: Comedy | E831: English | F831: France | G831: R
A832: Around the World in 80 Days | B832: 38020 | C832: Color | D832: Action | E832: English | F832: USA | G832: PG
A833: Babe: Pig in the City | B833: 35864 | C833: Color | D833: Adventure | E833: English | F833: Australia | G833: G
A834: Pan | B834: 42055 | C834: Color | D834: Adventure | E834: English | F834: USA | G834: PG
A835: Duplex | B835: 37669 | C835: Color | D835: Comedy | E835: English | F835: USA | G835: PG-13
A836: Nine | B836: 40135 | C836: Black and White | D836: Drama | E836: English | F836: USA | G836: PG-13
A837: The Gunman | B837: 42243 | C837: Color | D837: Action | E837: English | F837: USA | G837: R
A838: The Three Musketeers | B838: 40679 | C838: Color | D838: Action | E838: English | F838: Germany | G838: PG-13
A839: All the Pretty Horses | B839: 36599 | C839: Color | D839: Drama | E839: English | F839: USA | G839: PG-13
... A1036: Kingdom of the Spiders | B1036: 28127 | C1036: Color | D1036: Horror | E1036: English | F1036: USA | G1036: PG
A1037: Les couloirs du temps: Les visiteurs II | B1037: 36019 | C1037: Color | D1037: Comedy | E1037: French | F1037: France
A1038: Kites | B1038: 40284 | C1038: Color | D1038: Action | E1038: English | F1038: India
...
